octoprint_printerinfo/__init2__.py
octoprint_printerinfo/__init__.py
OctoPrint_Printerinfo-0.6.0.dist-info/METADATA
OctoPrint_Printerinfo-0.6.0.dist-info/WHEEL
OctoPrint_Printerinfo-0.6.0.dist-info/entry_points.txt
OctoPrint_Printerinfo-0.6.0.dist-info/top_level.txt
OctoPrint_Printerinfo-0.6.0.dist-info/RECORD
